[
    {
        "sura": 5,
        "ayah": 51,
        "line": 2,
        "centerX": 0.80451
    },
    {
        "sura": 5,
        "ayah": 52,
        "line": 4,
        "centerX": 0.33576
    },
    {
        "sura": 5,
        "ayah": 53,
        "line": 6,
        "centerX": 0.50486
    },
    {
        "sura": 5,
        "ayah": 54,
        "line": 10,
        "centerX": 0.85104
    },
    {
        "sura": 5,
        "ayah": 55,
        "line": 11,
        "centerX": 0.41076
    },
    {
        "sura": 5,
        "ayah": 56,
        "line": 12,
        "centerX": 0.32674
    },
    {
        "sura": 5,
        "ayah": 57,
        "line": 14,
        "centerX": 0.05264
    }
]